LICENSE
MANIFEST.in
README.md
setup.py
angularjs_compendium/__init__.py
angularjs_compendium/models.py
angularjs_compendium/templates/cms/plugins/bootstrap/carousel-slide.html
angularjs_compendium/templates/cms/plugins/bootstrap/carousel.html
angularjs_compendium/templates/cmsplugin_filer_image/image.html
djangocms_angular_compendium.egg-info/PKG-INFO
djangocms_angular_compendium.egg-info/SOURCES.txt
djangocms_angular_compendium.egg-info/dependency_links.txt
djangocms_angular_compendium.egg-info/not-zip-safe
djangocms_angular_compendium.egg-info/top_level.txt