Metadata-Version: 1.1
Name: djangocms-angular-compendium
Version: 0.1.0
Summary: Template overrides for DjangoCMS plugins when used with AngularJS
Home-page: https://github.com/jrief/djangocms-angular-compedium
Author: Jacob Rief
Author-email: jacob.rief@gmail.com
License: LICENSE-MIT
Platform: OS Independent
Classifier: Development Status :: 4 - Beta
Classifier: Environment :: Web Environment
Classifier: Framework :: Django
Classifier: Intended Audience :: Developers
Classifier: License :: OSI Approved :: MIT License
Classifier: Operating System :: OS Independent
Classifier: Programming Language :: Python
Classifier: Topic :: Internet :: WWW/HTTP :: Dynamic Content
